{"_path":"/2025/feb-fragments","_dir":"2025","_draft":false,"_partial":false,"_locale":"","title":"二月碎片：油糕、AI滥用、噪音、银行卡","description":null,"date":"2025-02-16T04:30:24.000Z","updated":null,"type":"story","categories":["生活"],"tags":["生活","家"],"readingTime":{"text":"3 min read","minutes":2.435,"time":146100,"words":487},"body":{"type":"root","children":[{"type":"element","tag":"h2","props":{"id":"油糕"},"children":[{"type":"text","value":"油糕"}]},{"type":"element","tag":"p","props":{},"children":[{"type":"text","value":"很久没有尝到手工现包的油糕了。"}]},{"type":"element","tag":"p","props":{},"children":[{"type":"text","value":"小时候，在宝鸡人民街的菜市场里，我有很多爱吃的摊位。胖子大饼、广式月饼、油糕糖糕，大多都是附近居民开办的摊位。胖子大饼是用面粉和油一圈一层地团起来，在大电饼铛里炕出来的厚而蓬松的圆烧饼，幼儿园放学时，我偶尔缠着家里人要买一张。奶奶见我喜欢得紧，常常买给我吃，又不忘说一句“好厨子，一把盐”。"}]},{"type":"element","tag":"p","props":{},"children":[{"type":"text","value":"上小学、初中时，买胖子大饼的夫妇去了外地，我又开始吃土家酱香饼了，依旧是油、面粉，还有一些酱料。就说陕西人是碳水脑袋吧，我能吃一个月家里做的臊子面也不会腻。"}]},{"type":"element","tag":"p","props":{},"children":[{"type":"text","value":"油糕也是我的心头好——也许是吃到了教训，我吃油糕不像前两者那样频繁，不然早早地也腻了——不，应该说腻了才好，这样我也不会苦苦寻找手工现包的油糕。"}]},{"type":"element","tag":"p","props":{},"children":[{"type":"text","value":"即使在人民街、永兴巷这样老城区摊贩云集的地方，也确实找不到手工油糕了。"}]},{"type":"element","tag":"p","props":{},"children":[{"type":"text","value":"先前和奶奶在这里逛时，看到了小吃摊上的油糕，奶奶讲：“这是你小时候爱吃的糖糕，要不要买一个？”我细细观察着，这油糕和我印象中的竟不一样了：它们整整齐齐地码起来，均一金黄、中心胀起，圆饼形状倒有些像是包着糖衣的药片。一口咬下，虽然软弹，内部空腔里也缠着糖液，但记忆中焦黄且酥得掉渣的外皮、厚实面皮里的浓稠糖浆，似乎都随着童年一起消逝了。"}]},{"type":"element","tag":"p","props":{},"children":[{"type":"text","value":"从那以后每次在爷爷奶奶家时，我都试图寻找小时候的味道。"}]}],"toc":{"title":"","searchDepth":4,"depth":4,"links":[{"id":"油糕","depth":2,"text":"油糕"}]}},"_type":"markdown","_id":"content:posts:2025:feb-fragments.md","_source":"content","_file":"posts/2025/feb-fragments.md","_stem":"posts/2025/feb-fragments","_extension":"md","_original_dir":"/posts"}